phab/tasks/__init__.py
phab/tasks/reconfirming_stellar_parameters.py
phab/tests/__init__.py
phab/tests/databases.py
phab/tests/datasets.py
phab/tests/files.py
phab/tests/math.py
phab/tests/strings.py
phab/utils/__init__.py
phab/utils/_version.py
phab/utils/databases/__init__.py
phab/utils/databases/lightcurves.py
phab/utils/databases/simbad.py
phab/utils/databases/tap.py
phab/utils/datasets/__init__.py
phab/utils/datasets/pandas.py
phab/utils/files/__init__.py
phab/utils/files/file.py
phab/utils/files/pickle.py
phab/utils/logs/__init__.py
phab/utils/logs/log.py
phab/utils/math/__init__.py
phab/utils/math/statistics.py
phab/utils/strings/__init__.py
phab/utils/strings/conversion.py
phab/utils/strings/extraction.py
phab_utils-2026.1.9.dist-info/licenses/LICENSE
phab_utils-2026.1.9.dist-info/METADATA
phab_utils-2026.1.9.dist-info/WHEEL
phab_utils-2026.1.9.dist-info/top_level.txt
phab_utils-2026.1.9.dist-info/RECORD
